Workbook

Sheet Dashboard
A1: Equity Price Targets — Dashboard
A2: Analyst consensus tracker · data via Yahoo Finance · auto-refreshed each trading day
A4: Tickers tracked | B4: =COUNTA('Price Targets'!A2:A1121)
A5: Tickers with live data | B5: =COUNT('Price Targets'!F2:F1121)
A6: Median upside to avg target | B6: =MEDIAN('Price Targets'!H2:H1121)
A7: Average dividend yield (payers) | B7: =AVERAGEIF('Price Targets'!O2:O1121,">0")
A8: Companies reporting in next 7 days | B8: =COUNTIFS('Price Targets'!Q2:Q1121,">="&TODAY(),'Price Targets'!Q2:Q1121,"<="&TODAY()+7)
A9: Largest upside to avg target | B9: =MAX('Price Targets'!H2:H1121)
A10: → ticker | B10: =INDEX('Price Targets'!A2:A1121,MATCH(MAX('Price Targets'!H2:H1121),'Price Targets'!H2:H1121,0))
A11: Smallest upside / largest downside | B11: =MIN('Price Targets'!H2:H1121)
A12: → ticker | B12: =INDEX('Price Targets'!A2:A1121,MATCH(MIN('Price Targets'!H2:H1121),'Price Targets'!H2:H1121,0))
A13: Combined market cap ($T) | B13: =SUM('Price Targets'!E2:E1121)/1000
A15: Data as of: 2026-10-28 01:32
A16: Legend: green = trading below analyst targets (upside), red = above (downside). Yellow earnings dates are within 7 days.

Sheet Price Targets
A1: Ticker | B1: Company | C1: Industry | D1: Country | E1: Market Cap ($B) | F1: Price ($) | G1: Avg Target ($) | H1: Upside to Avg (%) | I1: Min Target ($) | J1: Upside to Min (%) | K1: Max Target ($) | L1: Upside to Max (%) | M1: # Analysts | N1: Annual Div/Share ($) | O1: Div Yield (%) | P1: Ex-Div Date | Q1: Earnings Date | R1: TTM EPS ($) | S1: TTM P/E (x) | T1: Data As Of
A2: NVDA | B2: NVIDIA Corporation | C2: Semiconductors | D2: United States | E2: 5262.6 | F2: 217.94 | G2: 328.95346 | H2: =IF(AND(ISNUMBER(F2),ISNUMBER(G2),F2>0),G2/F2-1,"") | I2: 180 | J2: =IF(AND(ISNUMBER(F2),ISNUMBER(I2),F2>0),I2/F2-1,"") | K2: 515 | L2: =IF(AND(ISNUMBER(F2),ISNUMBER(K2),F2>0),K2/F2-1,"") | M2: 58 | N2: 1 | O2: =IF(AND(ISNUMBER(F2),ISNUMBER(N2),F2>0),N2/F2,"") | P2: 46275 | Q2: 46343 | R2: 7.91 | S2: =IF(AND(ISNUMBER(F2),ISNUMBER(R2),R2>0),F2/R2,"") | T2: 46323
A3: AAPL | B3: Apple Inc. | C3: Consumer Electronics | D3: United States | E3: 5065.64 | F3: 347.1 | G3: 330.0169 | H3: =IF(AND(ISNUMBER(F3),ISNUMBER(G3),F3>0),G3/F3-1,"") | I3: 240 | J3: =IF(AND(ISNUMBER(F3),ISNUMBER(I3),F3>0),I3/F3-1,"") | K3: 405 | L3: =IF(AND(ISNUMBER(F3),ISNUMBER(K3),F3>0),K3/F3-1,"") | M3: 39 | N3: 1.08 | O3: =IF(AND(ISNUMBER(F3),ISNUMBER(N3),F3>0),N3/F3,"") | P3: 46244 | Q3: 46328 | R3: 8.72 | S3: =IF(AND(ISNUMBER(F3),ISNUMBER(R3),R3>0),F3/R3,"") | T3: 46323
A4: MSFT | B4: Microsoft Corporation | C4: Software - Infrastructure | D4: United States | E4: 3945.42 | F4: 531.33 | G4: 605.1243 | H4: =IF(AND(ISNUMBER(F4),ISNUMBER(G4),F4>0),G4/F4-1,"") | I4: 440 | J4: =IF(AND(ISNUMBER(F4),ISNUMBER(I4),F4>0),I4/F4-1,"") | K4: 870 | L4: =IF(AND(ISNUMBER(F4),ISNUMBER(K4),F4>0),K4/F4-1,"") | M4: 53 | N4: 3.92 | O4: =IF(AND(ISNUMBER(F4),ISNUMBER(N4),F4>0),N4/F4,"") | P4: 46345 | Q4: 46323 | R4: 17.95 | S4: =IF(AND(ISNUMBER(F4),ISNUMBER(R4),R4>0),F4/R4,"") | T4: 46323
A5: GOOGL | B5: Alphabet Inc. | C5: Internet Content & Information | D5: United States | E5: 3920.67 | F5: 320.58 | G5: 429.12222 | H5: =IF(AND(ISNUMBER(F5),ISNUMBER(G5),F5>0),G5/F5-1,"") | I5: 340 | J5: =IF(AND(ISNUMBER(F5),ISNUMBER(I5),F5>0),I5/F5-1,"") | K5: 500 | L5: =IF(AND(ISNUMBER(F5),ISNUMBER(K5),F5>0),K5/F5-1,"") | M5: 54 | N5: 0.88 | O5: =IF(AND(ISNUMBER(F5),ISNUMBER(N5),F5>0),N5/F5,"") | P5: 46269 | Q5: 46323 | R5: 19.93 | S5: =IF(AND(ISNUMBER(F5),ISNUMBER(R5),R5>0),F5/R5,"") | T5: 46323
A6: AMZN | B6: Amazon.com, Inc. | C6: Internet Retail | D6: United States | E6: 2730.02 | F6: 253.1 | G6: 332.2369 | H6: =IF(AND(ISNUMBER(F6),ISNUMBER(G6),F6>0),G6/F6-1,"") | I6: 230 | J6: =IF(AND(ISNUMBER(F6),ISNUMBER(I6),F6>0),I6/F6-1,"") | K6: 405 | L6: =IF(AND(ISNUMBER(F6),ISNUMBER(K6),F6>0),K6/F6-1,"") | M6: 58 | O6: =IF(AND(ISNUMBER(F6),ISNUMBER(N6),F6>0),N6/F6,"") | Q6: 46324 | R6: 12.43 | S6: =IF(AND(ISNUMBER(F6),ISNUMBER(R6),R6>0),F6/R6,"") | T6: 46323
A7: TSM | B7: Taiwan Semiconductor Manufactur | C7: Semiconductors | D7: Taiwan | E7: 2265.81 | F7: 436.87 | G7: 584.39294 | H7: =IF(AND(ISNUMBER(F7),ISNUMBER(G7),F7>0),G7/F7-1,"") | I7: 440 | J7: =IF(AND(ISNUMBER(F7),ISNUMBER(I7),F7>0),I7/F7-1,"") | K7: 1000 | L7: =IF(AND(ISNUMBER(F7),ISNUMBER(K7),F7>0),K7/F7-1,"") | M7: 20 | N7: 3.77 | O7: =IF(AND(ISNUMBER(F7),ISNUMBER(N7),F7>0),N7/F7,"") | P7: 46366 | Q7: 46401 | R7: 15.43 | S7: =IF(AND(ISNUMBER(F7),ISNUMBER(R7),R7>0),F7/R7,"") | T7: 46323
A8: SPCX | B8: Space Exploration Technologies | C8: Aerospace & Defense | D8: United States | E8: 2017.87 | F8: 148.58 | G8: 256.58667 | H8: =IF(AND(ISNUMBER(F8),ISNUMBER(G8),F8>0),G8/F8-1,"") | I8: 70 | J8: =IF(AND(ISNUMBER(F8),ISNUMBER(I8),F8>0),I8/F8-1,"") | K8: 800 | L8: =IF(AND(ISNUMBER(F8),ISNUMBER(K8),F8>0),K8/F8-1,"") | M8: 36 | O8: =IF(AND(ISNUMBER(F8),ISNUMBER(N8),F8>0),N8/F8,"") | Q8: 46315 | R8: 0.23 | S8: =IF(AND(ISNUMBER(F8),ISNUMBER(R8),R8>0),F8/R8,"") | T8: 46323
A9: AVGO | B9: Broadcom Inc. | C9: Semiconductors | D9: United States | E9: 1634.16 | F9: 342.33 | G9: 530.14166 | H9: =IF(AND(ISNUMBER(F9),ISNUMBER(G9),F9>0),G9/F9-1,"") | I9: 215.88 | J9: =IF(AND(ISNUMBER(F9),ISNUMBER(I9),F9>0),I9/F9-1,"") | K9: 660 | L9: =IF(AND(ISNUMBER(F9),ISNUMBER(K9),F9>0),K9/F9-1,"") | M9: 48 | N9: 2.6 | O9: =IF(AND(ISNUMBER(F9),ISNUMBER(N9),F9>0),N9/F9,"") | P9: 46286 | Q9: 46365 | R9: 7.83 | S9: =IF(AND(ISNUMBER(F9),ISNUMBER(R9),R9>0),F9/R9,"") | T9: 46323
A10: TSLA | B10: Tesla, Inc. | C10: Auto Manufacturers | D10: United States | E10: 1610.58 | F10: 407.46 | G10: 410.68256 | H10: =IF(AND(ISNUMBER(F10),ISNUMBER(G10),F10>0),G10/F10-1,"") | I10: 128.11 | J10: =IF(AND(ISNUMBER(F10),ISNUMBER(I10),F10>0),I10/F10-1,"") | K10: 600 | L10: =IF(AND(ISNUMBER(F10),ISNUMBER(K10),F10>0),K10/F10-1,"") | M10: 39 | O10: =IF(AND(ISNUMBER(F10),ISNUMBER(N10),F10>0),N10/F10,"") | Q10: 46316 | R10: 0.91 | S10: =IF(AND(ISNUMBER(F10),ISNUMBER(R10),R10>0),F10/R10,"") | T10: 46323
A11: META | B11: Meta Platforms, Inc. | C11: Internet Content & Information | D11: United States | E11: 1585.72 | F11: 620.19 | G11: 846.79034 | H11: =IF(AND(ISNUMBER(F11),ISNUMBER(G11),F11>0),G11/F11-1,"") | I11: 629.06 | J11: =IF(AND(ISNUMBER(F11),ISNUMBER(I11),F11>0),I11/F11-1,"") | K11: 1050 | L11: =IF(AND(ISNUMBER(F11),ISNUMBER(K11),F11>0),K11/F11-1,"") | M11: 58 | N11: 2.1 | O11: =IF(AND(ISNUMBER(F11),ISNUMBER(N11),F11>0),N11/F11,"") | P11: 46286 | Q11: 46316 | R11: 29.31 | S11: =IF(AND(ISNUMBER(F11),ISNUMBER(R11),R11>0),F11/R11,"") | T11: 46323
A12: BRK.B | B12: Berkshire Hathaway Inc. New | C12: Insurance - Diversified | D12: United States | E12: 1162.38 | F12: 542.99 | G12: 555.6667 | H12: =IF(AND(ISNUMBER(F12),ISNUMBER(G12),F12>0),G12/F12-1,"") | I12: 510 | J12: =IF(AND(ISNUMBER(F12),ISNUMBER(I12),F12>0),I12/F12-1,"") | K12: 628 | L12: =IF(AND(ISNUMBER(F12),ISNUMBER(K12),F12>0),K12/F12-1,"") | M12: 3 | O12: =IF(AND(ISNUMBER(F12),ISNUMBER(N12),F12>0),N12/F12,"") | Q12: 46333 | R12: 39.76 | S12: =IF(AND(ISNUMBER(F12),ISNUMBER(R12),R12>0),F12/R12,"") | T12: 46323
A13: BRK.A | B13: Berkshire Hathaway Inc. | C13: Insurance - Diversified | D13: United States | E13: 1156.13 | F13: 810106 | G13: 808601.25 | H13: =IF(AND(ISNUMBER(F13),ISNUMBER(G13),F13>0),G13/F13-1,"") | I13: 735000 | J13: =IF(AND(ISNUMBER(F13),ISNUMBER(I13),F13>0),I13/F13-1,"") | K13: 942405 | L13: =IF(AND(ISNUMBER(F13),ISNUMBER(K13),F13>0),K13/F13-1,"") | M13: 4 | O13: =IF(AND(ISNUMBER(F13),ISNUMBER(N13),F13>0),N13/F13,"") | Q13: 46333 | R13: 59636.03 | S13: =IF(AND(ISNUMBER(F13),ISNUMBER(R13),R13>0),F13/R13,"") | T13: 46323
A14: LLY | B14: Eli Lilly and Company | C14: Drug Manufacturers - General | D14: United States | E14: 1143.13 | F14: 1281.91 | G14: 1333.7213 | H14: =IF(AND(ISNUMBER(F14),ISNUMBER(G14),F14>0),G14/F14-1,"") | I14: 930 | J14: =IF(AND(ISNUMBER(F14),ISNUMBER(I14),F14>0),I14/F14-1,"") | K14: 1600 | L14: =IF(AND(ISNUMBER(F14),ISNUMBER(K14),F14>0),K14/F14-1,"") | M14: 30 | N14: 6.92 | O14: =IF(AND(ISNUMBER(F14),ISNUMBER(N14),F14>0),N14/F14,"") | P14: 46339 | Q14: 46324 | R14: 29.79 | S14: =IF(AND(ISNUMBER(F14),ISNUMBER(R14),R14>0),F14/R14,"") | T14: 46323
A15: MU | B15: Micron Technology, Inc. | C15: Semiconductors | D15: United States | E15: 1050.82 | F15: 928.76 | G15: 1561.9111 | H15: =IF(AND(ISNUMBER(F15),ISNUMBER(G15),F15>0),G15/F15-1,"") | I15: 361 | J15: =IF(AND(ISNUMBER(F15),ISNUMBER(I15),F15>0),I15/F15-1,"") | K15: 3000 | L15: =IF(AND(ISNUMBER(F15),ISNUMBER(K15),F15>0),K15/F15-1,"") | M15: 45 | N15: 0.6 | O15: =IF(AND(ISNUMBER(F15),ISNUMBER(N15),F15>0),N15/F15,"") | P15: 46309 | Q15: 46379 | R15: 74.33 | S15: =IF(AND(ISNUMBER(F15),ISNUMBER(R15),R15>0),F15/R15,"") | T15: 46323
A16: SKHY | B16: SK hynix Inc. | C16: Semiconductors | D16: South Korea | E16: 1025.04 | F16: 145.36 | G16: 243.42857 | H16: =IF(AND(ISNUMBER(F16),ISNUMBER(G16),F16>0),G16/F16-1,"") | I16: 152 | J16: =IF(AND(ISNUMBER(F16),ISNUMBER(I16),F16>0),I16/F16-1,"") | K16: 320 | L16: =IF(AND(ISNUMBER(F16),ISNUMBER(K16),F16>0),K16/F16-1,"") | M16: 14 | N16: 0.11 | O16: =IF(AND(ISNUMBER(F16),ISNUMBER(N16),F16>0),N16/F16,"") | P16: 46265 | Q16: 46322 | R16: 15.68 | S16: =IF(AND(ISNUMBER(F16),ISNUMBER(R16),R16>0),F16/R16,"") | T16: 46323
A17: WMT | B17: Walmart Inc. | C17: Discount Stores | D17: United States | E17: 949.56 | F17: 119.32 | G17: 127.475 | H17: =IF(AND(ISNUMBER(F17),ISNUMBER(G17),F17>0),G17/F17-1,"") | I17: 81 | J17: =IF(AND(ISNUMBER(F17),ISNUMBER(I17),F17>0),I17/F17-1,"") | K17: 155 | L17: =IF(AND(ISNUMBER(F17),ISNUMBER(K17),F17>0),K17/F17-1,"") | M17: 40 | N17: 0.99 | O17: =IF(AND(ISNUMBER(F17),ISNUMBER(N17),F17>0),N17/F17,"") | P17: 46367 | Q17: 46345 | R17: 2.76 | S17: =IF(AND(ISNUMBER(F17),ISNUMBER(R17),R17>0),F17/R17,"") | T17: 46323
A18: AMD | B18: Advanced Micro Devices, Inc. | C18: Semiconductors | D18: United States | E18: 914.61 | F18: 560.26 | G18: 637.608 | H18: =IF(AND(ISNUMBER(F18),ISNUMBER(G18),F18>0),G18/F18-1,"") | I18: 365 | J18: =IF(AND(ISNUMBER(F18),ISNUMBER(I18),F18>0),I18/F18-1,"") | K18: 1250 | L18: =IF(AND(ISNUMBER(F18),ISNUMBER(K18),F18>0),K18/F18-1,"") | M18: 50 | O18: =IF(AND(ISNUMBER(F18),ISNUMBER(N18),F18>0),N18/F18,"") | Q18: 46329 | R18: 3.92 | S18: =IF(AND(ISNUMBER(F18),ISNUMBER(R18),R18>0),F18/R18,"") | T18: 46323
A19: JPM | B19: JP Morgan Chase & Co. | C19: Banks - Diversified | D19: United States | E19: 891.72 | F19: 335.79 | G19: 372.26086 | H19: =IF(AND(ISNUMBER(F19),ISNUMBER(G19),F19>0),G19/F19-1,"") | I19: 312 | J19: =IF(AND(ISNUMBER(F19),ISNUMBER(I19),F19>0),I19/F19-1,"") | K19: 425 | L19: =IF(AND(ISNUMBER(F19),ISNUMBER(K19),F19>0),K19/F19-1,"") | M19: 23 | N19: 6.6 | O19: =IF(AND(ISNUMBER(F19),ISNUMBER(N19),F19>0),N19/F19,"") | P19: 46301 | Q19: 46401 | R19: 23.84 | S19: =IF(AND(ISNUMBER(F19),ISNUMBER(R19),R19>0),F19/R19,"") | T19: 46323
A20: V | B20: Visa Inc. | C20: Credit Services | D20: United States | E20: 754.43 | F20: 401.86 | G20: 426.82108 | H20: =IF(AND(ISNUMBER(F20),ISNUMBER(G20),F20>0),G20/F20-1,"") | I20: 330 | J20: =IF(AND(ISNUMBER(F20),ISNUMBER(I20),F20>0),I20/F20-1,"") | K20: 480 | L20: =IF(AND(ISNUMBER(F20),ISNUMBER(K20),F20>0),K20/F20-1,"") | M20: 37 | N20: 2.68 | O20: =IF(AND(ISNUMBER(F20),ISNUMBER(N20),F20>0),N20/F20,"") | P20: 46245 | Q20: 46322 | R20: 11.75 | S20: =IF(AND(ISNUMBER(F20),ISNUMBER(R20),R20>0),F20/R20,"") | T20: 46323
A21: XOM | B21: ExxonMobil Holdings Corporation | C21: Oil & Gas Integrated | D21: United States | E21: 739.77 | F21: 179.91 | G21: 179.40909 | H21: =IF(AND(ISNUMBER(F21),ISNUMBER(G21),F21>0),G21/F21-1,"") | I21: 142 | J21: =IF(AND(ISNUMBER(F21),ISNUMBER(I21),F21>0),I21/F21-1,"") | K21: 206 | L21: =IF(AND(ISNUMBER(F21),ISNUMBER(K21),F21>0),K21/F21-1,"") | M21: 22 | N21: 4.12 | O21: =IF(AND(ISNUMBER(F21),ISNUMBER(N21),F21>0),N21/F21,"") | P21: 46251 | Q21: 46325 | R21: 7.77 | S21: =IF(AND(ISNUMBER(F21),ISNUMBER(R21),R21>0),F21/R21,"") | T21: 46323
A22: JNJ | B22: Johnson & Johnson | C22: Drug Manufacturers - General | D22: United States | E22: 646.92 | F22: 268.73 | G22: 279.4091 | H22: =IF(AND(ISNUMBER(F22),ISNUMBER(G22),F22>0),G22/F22-1,"") | I22: 190 | J22: =IF(AND(ISNUMBER(F22),ISNUMBER(I22),F22>0),I22/F22-1,"") | K22: 320 | L22: =IF(AND(ISNUMBER(F22),ISNUMBER(K22),F22>0),K22/F22-1,"") | M22: 22 | N22: 5.36 | O22: =IF(AND(ISNUMBER(F22),ISNUMBER(N22),F22>0),N22/F22,"") | P22: 46350 | Q22: 46308 | R22: 6.59 | S22: =IF(AND(ISNUMBER(F22),ISNUMBER(R22),R22>0),F22/R22,"") | T22: 46323
A23: ASML | B23: ASML Holding N.V. - New York Re | C23: Semiconductor Equipment & Materials | D23: Netherlands | E23: 630.38 | F23: 1635.57 | G23: 2134.3977 | H23: =IF(AND(ISNUMBER(F23),ISNUMBER(G23),F23>0),G23/F23-1,"") | I23: 860.9393 | J23: =IF(AND(ISNUMBER(F23),ISNUMBER(I23),F23>0),I23/F23-1,"") | K23: 2828.1382 | L23: =IF(AND(ISNUMBER(F23),ISNUMBER(K23),F23>0),K23/F23-1,"") | M23: 17 | N23: 9.08 | O23: =IF(AND(ISNUMBER(F23),ISNUMBER(N23),F23>0),N23/F23,"") | P23: 46322 | Q23: 46309 | R23: 40.64 | S23: =IF(AND(ISNUMBER(F23),ISNUMBER(R23),R23>0),F23/R23,"") | T23: 46323
A24: MA | B24: Mastercard Incorporated | C24: Credit Services | D24: United States | E24: 534.23 | F24: 609.85 | G24: 676.0381 | H24: =IF(AND(ISNUMBER(F24),ISNUMBER(G24),F24>0),G24/F24-1,"") | I24: 550 | J24: =IF(AND(ISNUMBER(F24),ISNUMBER(I24),F24>0),I24/F24-1,"") | K24: 765 | L24: =IF(AND(ISNUMBER(F24),ISNUMBER(K24),F24>0),K24/F24-1,"") | M24: 37 | N24: 3.48 | O24: =IF(AND(ISNUMBER(F24),ISNUMBER(N24),F24>0),N24/F24,"") | P24: 46304 | Q24: 46324 | R24: 18.18 | S24: =IF(AND(ISNUMBER(F24),ISNUMBER(R24),R24>0),F24/R24,"") | T24: 46323
A25: ABBV | B25: AbbVie Inc. | C25: Drug Manufacturers - General | D25: United States | E25: 506.08 | F25: 286.39 | G25: 283.18518 | H25: =IF(AND(ISNUMBER(F25),ISNUMBER(G25),F25>0),G25/F25-1,"") | I25: 200 | J25: =IF(AND(ISNUMBER(F25),ISNUMBER(I25),F25>0),I25/F25-1,"") | K25: 325 | L25: =IF(AND(ISNUMBER(F25),ISNUMBER(K25),F25>0),K25/F25-1,"") | M25: 27 | N25: 6.92 | O25: =IF(AND(ISNUMBER(F25),ISNUMBER(N25),F25>0),N25/F25,"") | P25: 46310 | Q25: 46325 | R25: 3.55 | S25: =IF(AND(ISNUMBER(F25),ISNUMBER(R25),R25>0),F25/R25,"") | T25: 46323
A26: INTC | B26: Intel Corporation | C26: Semiconductors | D26: United States | E26: 495.52 | F26: 93.74 | G26: 117.71429 | H26: =IF(AND(ISNUMBER(F26),ISNUMBER(G26),F26>0),G26/F26-1,"") | I26: 80 | J26: =IF(AND(ISNUMBER(F26),ISNUMBER(I26),F26>0),I26/F26-1,"") | K26: 200 | L26: =IF(AND(ISNUMBER(F26),ISNUMBER(K26),F26>0),K26/F26-1,"") | M26: 42 | O26: =IF(AND(ISNUMBER(F26),ISNUMBER(N26),F26>0),N26/F26,"") | Q26: 46324 | R26: -2.12 | S26: =IF(AND(ISNUMBER(F26),ISNUMBER(R26),R26>0),F26/R26,"") | T26: 46323
A27: PLTR | B27: Palantir Technologies Inc. | C27: Software - Infrastructure | D27: United States | E27: 477.56 | F27: 198.73 | G27: 208.96538 | H27: =IF(AND(ISNUMBER(F27),ISNUMBER(G27),F27>0),G27/F27-1,"") | I27: 80 | J27: =IF(AND(ISNUMBER(F27),ISNUMBER(I27),F27>0),I27/F27-1,"") | K27: 265 | L27: =IF(AND(ISNUMBER(F27),ISNUMBER(K27),F27>0),K27/F27-1,"") | M27: 26 | O27: =IF(AND(ISNUMBER(F27),ISNUMBER(N27),F27>0),N27/F27,"") | Q27: 46328 | R27: 1.17 | S27: =IF(AND(ISNUMBER(F27),ISNUMBER(R27),R27>0),F27/R27,"") | T27: 46323
A28: CVX | B28: Chevron Corporation | C28: Oil & Gas Integrated | D28: United States | E28: 447.7 | F28: 228.23 | G28: 232.5 | H28: =IF(AND(ISNUMBER(F28),ISNUMBER(G28),F28>0),G28/F28-1,"") | I28: 175 | J28: =IF(AND(ISNUMBER(F28),ISNUMBER(I28),F28>0),I28/F28-1,"") | K28: 272 | L28: =IF(AND(ISNUMBER(F28),ISNUMBER(K28),F28>0),K28/F28-1,"") | M28: 24 | N28: 7.12 | O28: =IF(AND(ISNUMBER(F28),ISNUMBER(N28),F28>0),N28/F28,"") | P28: 46253 | Q28: 46325 | R28: 10.39 | S28: =IF(AND(ISNUMBER(F28),ISNUMBER(R28),R28>0),F28/R28,"") | T28: 46323
A29: TCEHY | B29: Tencent Holding Ltd. | C29: Internet Content & Information | D29: China | E29: 445.37 | F29: 49.46 | G29: 88.25606 | H29: =IF(AND(ISNUMBER(F29),ISNUMBER(G29),F29>0),G29/F29-1,"") | I29: 80.06239 | J29: =IF(AND(ISNUMBER(F29),ISNUMBER(I29),F29>0),I29/F29-1,"") | K29: 99.67857 | L29: =IF(AND(ISNUMBER(F29),ISNUMBER(K29),F29>0),K29/F29-1,"") | M29: 4 | N29: 0.67 | O29: =IF(AND(ISNUMBER(F29),ISNUMBER(N29),F29>0),N29/F29,"") | P29: 46160 | Q29: 46344 | R29: 3.64 | S29: =IF(AND(ISNUMBER(F29),ISNUMBER(R29),R29>0),F29/R29,"") | T29: 46323
A30: COST | B30: Costco Wholesale Corporation | C30: Discount Stores | D30: United States | E30: 439.64 | F30: 992.13 | G30: 1067.5946 | H30: =IF(AND(ISNUMBER(F30),ISNUMBER(G30),F30>0),G30/F30-1,"") | I30: 770 | J30: =IF(AND(ISNUMBER(F30),ISNUMBER(I30),F30>0),I30/F30-1,"") | K30: 1315 | L30: =IF(AND(ISNUMBER(F30),ISNUMBER(K30),F30>0),K30/F30-1,"") | M30: 37 | N30: 5.88 | O30: =IF(AND(ISNUMBER(F30),ISNUMBER(N30),F30>0),N30/F30,"") | P30: 46325 | Q30: 46366 | R30: 20.76 | S30: =IF(AND(ISNUMBER(F30),ISNUMBER(R30),R30>0),F30/R30,"") | T30: 46323
A31: CSCO | B31: Cisco Systems, Inc. | C31: Communication Equipment | D31: United States | E31: 439.13 | F31: 111.38 | G31: 136.16 | H31: =IF(AND(ISNUMBER(F31),ISNUMBER(G31),F31>0),G31/F31-1,"") | I31: 110 | J31: =IF(AND(ISNUMBER(F31),ISNUMBER(I31),F31>0),I31/F31-1,"") | K31: 170 | L31: =IF(AND(ISNUMBER(F31),ISNUMBER(K31),F31>0),K31/F31-1,"") | M31: 25 | N31: 1.68 | O31: =IF(AND(ISNUMBER(F31),ISNUMBER(N31),F31>0),N31/F31,"") | P31: 46297 | Q31: 46338 | R31: 3.33 | S31: =IF(AND(ISNUMBER(F31),ISNUMBER(R31),R31>0),F31/R31,"") | T31: 46323
A32: ORCL | B32: Oracle Corporation | C32: Software - Infrastructure | D32: United States | E32: 395.7 | F32: 130.53 | G32: 235.8034 | H32: =IF(AND(ISNUMBER(F32),ISNUMBER(G32),F32>0),G32/F32-1,"") | I32: 110 | J32: =IF(AND(ISNUMBER(F32),ISNUMBER(I32),F32>0),I32/F32-1,"") | K32: 400 | L32: =IF(AND(ISNUMBER(F32),ISNUMBER(K32),F32>0),K32/F32-1,"") | M32: 41 | N32: 2 | O32: =IF(AND(ISNUMBER(F32),ISNUMBER(N32),F32>0),N32/F32,"") | P32: 46304 | Q32: 46370 | R32: 6.38 | S32: =IF(AND(ISNUMBER(F32),ISNUMBER(R32),R32>0),F32/R32,"") | T32: 46323
A33: KO | B33: Coca-Cola Company (The) | C33: Beverages - Non-Alcoholic | D33: United States | E33: 392.31 | F33: 91.18 | G33: 95.625 | H33: =IF(AND(ISNUMBER(F33),ISNUMBER(G33),F33>0),G33/F33-1,"") | I33: 80 | J33: =IF(AND(ISNUMBER(F33),ISNUMBER(I33),F33>0),I33/F33-1,"") | K33: 104 | L33: =IF(AND(ISNUMBER(F33),ISNUMBER(K33),F33>0),K33/F33-1,"") | M33: 24 | N33: 2.12 | O33: =IF(AND(ISNUMBER(F33),ISNUMBER(N33),F33>0),N33/F33,"") | P33: 46357 | Q33: 46322 | R33: 3.33 | S33: =IF(AND(ISNUMBER(F33),ISNUMBER(R33),R33>0),F33/R33,"") | T33: 46323
A34: RHHBY | B34: Roche Holding Ltd | C34: Drug Manufacturers - General | D34: Switzerland | E34: 384.42 | F34: 60.31 | G34: 60.01429 | H34: =IF(AND(ISNUMBER(F34),ISNUMBER(G34),F34>0),G34/F34-1,"") | I34: 52 | J34: =IF(AND(ISNUMBER(F34),ISNUMBER(I34),F34>0),I34/F34-1,"") | K34: 67.1 | L34: =IF(AND(ISNUMBER(F34),ISNUMBER(K34),F34>0),K34/F34-1,"") | M34: 7 | N34: 1.55 | O34: =IF(AND(ISNUMBER(F34),ISNUMBER(N34),F34>0),N34/F34,"") | P34: 46094 | Q34: 46051 | R34: 2.41 | S34: =IF(AND(ISNUMBER(F34),ISNUMBER(R34),R34>0),F34/R34,"") | T34: 46323
A35: PG | B35: Procter & Gamble Company (The) | C35: Household & Personal Products | D35: United States | E35: 369.06 | F35: 159.23 | G35: 173.30435 | H35: =IF(AND(ISNUMBER(F35),ISNUMBER(G35),F35>0),G35/F35-1,"") | I35: 143 | J35: =IF(AND(ISNUMBER(F35),ISNUMBER(I35),F35>0),I35/F35-1,"") | K35: 190 | L35: =IF(AND(ISNUMBER(F35),ISNUMBER(K35),F35>0),K35/F35-1,"") | M35: 23 | N35: 4.35 | O35: =IF(AND(ISNUMBER(F35),ISNUMBER(N35),F35>0),N35/F35,"") | P35: 46318 | Q35: 46408 | R35: 6.64 | S35: =IF(AND(ISNUMBER(F35),ISNUMBER(R35),R35>0),F35/R35,"") | T35: 46323
A36: UNH | B36: UnitedHealth Group Incorporated | C36: Healthcare Plans | D36: United States | E36: 368.36 | F36: 410.39 | G36: 476.64 | H36: =IF(AND(ISNUMBER(F36),ISNUMBER(G36),F36>0),G36/F36-1,"") | I36: 380 | J36: =IF(AND(ISNUMBER(F36),ISNUMBER(I36),F36>0),I36/F36-1,"") | K36: 531 | L36: =IF(AND(ISNUMBER(F36),ISNUMBER(K36),F36>0),K36/F36-1,"") | M36: 25 | N36: 9.28 | O36: =IF(AND(ISNUMBER(F36),ISNUMBER(N36),F36>0),N36/F36,"") | P36: 46279 | Q36: 46399 | R36: 15.55 | S36: =IF(AND(ISNUMBER(F36),ISNUMBER(R36),R36>0),F36/R36,"") | T36: 46323
A37: BAC | B37: Bank of America Corporation | C37: Banks - Diversified | D37: United States | E37: 350.84 | F37: 50.68 | G37: 62.95455 | H37: =IF(AND(ISNUMBER(F37),ISNUMBER(G37),F37>0),G37/F37-1,"") | I37: 56 | J37: =IF(AND(ISNUMBER(F37),ISNUMBER(I37),F37>0),I37/F37-1,"") | K37: 71 | L37: =IF(AND(ISNUMBER(F37),ISNUMBER(K37),F37>0),K37/F37-1,"") | M37: 22 | N37: 1.28 | O37: =IF(AND(ISNUMBER(F37),ISNUMBER(N37),F37>0),N37/F37,"") | P37: 46360 | Q37: 46402 | R37: 4.19 | S37: =IF(AND(ISNUMBER(F37),ISNUMBER(R37),R37>0),F37/R37,"") | T37: 46323
A38: MRK | B38: Merck & Company, Inc. | C38: Drug Manufacturers - General | D38: United States | E38: 349.89 | F38: 141.82 | G38: 159.76 | H38: =IF(AND(ISNUMBER(F38),ISNUMBER(G38),F38>0),G38/F38-1,"") | I38: 105 | J38: =IF(AND(ISNUMBER(F38),ISNUMBER(I38),F38>0),I38/F38-1,"") | K38: 186 | L38: =IF(AND(ISNUMBER(F38),ISNUMBER(K38),F38>0),K38/F38-1,"") | M38: 25 | N38: 3.4 | O38: =IF(AND(ISNUMBER(F38),ISNUMBER(N38),F38>0),N38/F38,"") | P38: 46280 | Q38: 46324 | R38: 1.24 | S38: =IF(AND(ISNUMBER(F38),ISNUMBER(R38),R38>0),F38/R38,"") | T38: 46323
A39: PANW | B39: Palo Alto Networks, Inc. | C39: Software - Infrastructure | D39: United States | E39: 328.59 | F39: 401.7 | G39: 398.52 | H39: =IF(AND(ISNUMBER(F39),ISNUMBER(G39),F39>0),G39/F39-1,"") | I39: 190 | J39: =IF(AND(ISNUMBER(F39),ISNUMBER(I39),F39>0),I39/F39-1,"") | K39: 525 | L39: =IF(AND(ISNUMBER(F39),ISNUMBER(K39),F39>0),K39/F39-1,"") | M39: 50 | O39: =IF(AND(ISNUMBER(F39),ISNUMBER(N39),F39>0),N39/F39,"") | Q39: 46345 | R39: 0.4 | S39: =IF(AND(ISNUMBER(F39),ISNUMBER(R39),R39>0),F39/R39,"") | T39: 46323
A40: CAT | B40: Caterpillar, Inc. | C40: Farm & Heavy Construction Machinery | D40: United States | E40: 327.89 | F40: 713.31 | G40: 926.9139 | H40: =IF(AND(ISNUMBER(F40),ISNUMBER(G40),F40>0),G40/F40-1,"") | I40: 575 | J40: =IF(AND(ISNUMBER(F40),ISNUMBER(I40),F40>0),I40/F40-1,"") | K40: 1150 | L40: =IF(AND(ISNUMBER(F40),ISNUMBER(K40),F40>0),K40/F40-1,"") | M40: 26 | N40: 6.52 | O40: =IF(AND(ISNUMBER(F40),ISNUMBER(N40),F40>0),N40/F40,"") | P40: 46321 | Q40: 46324 | R40: 23.23 | S40: =IF(AND(ISNUMBER(F40),ISNUMBER(R40),R40>0),F40/R40,"") | T40: 46323
A41: DELL | B41: Dell Technologies Inc. | C41: Computer Hardware | D41: United States | E41: 319.15 | F41: 501.96 | G41: 595 | H41: =IF(AND(ISNUMBER(F41),ISNUMBER(G41),F41>0),G41/F41-1,"") | I41: 490 | J41: =IF(AND(ISNUMBER(F41),ISNUMBER(I41),F41>0),I41/F41-1,"") | K41: 735 | L41: =IF(AND(ISNUMBER(F41),ISNUMBER(K41),F41>0),K41/F41-1,"") | M41: 25 | N41: 2.52 | O41: =IF(AND(ISNUMBER(F41),ISNUMBER(N41),F41>0),N41/F41,"") | P41: 46315 | Q41: 46353 | R41: 17.2 | S41: =IF(AND(ISNUMBER(F41),ISNUMBER(R41),R41>0),F41/R41,"") | T41: 46323
A42: HD | B42: Home Depot, Inc. (The) | C42: Home Improvement Retail | D42: United States | E42: 317.76 | F42: 318.5 | G42: 379 | H42: =IF(AND(ISNUMBER(F42),ISNUMBER(G42),F42>0),G42/F42-1,"") | I42: 310 | J42: =IF(AND(ISNUMBER(F42),ISNUMBER(I42),F42>0),I42/F42-1,"") | K42: 425 | L42: =IF(AND(ISNUMBER(F42),ISNUMBER(K42),F42>0),K42/F42-1,"") | M42: 32 | N42: 9.32 | O42: =IF(AND(ISNUMBER(F42),ISNUMBER(N42),F42>0),N42/F42,"") | P42: 46268 | Q42: 46343 | R42: 14.29 | S42: =IF(AND(ISNUMBER(F42),ISNUMBER(R42),R42>0),F42/R42,"") | T42: 46323
A43: PM | B43: Philip Morris International Inc | C43: Tobacco | D43: United States | E43: 315.81 | F43: 202.62 | G43: 210.46667 | H43: =IF(AND(ISNUMBER(F43),ISNUMBER(G43),F43>0),G43/F43-1,"") | I43: 175 | J43: =IF(AND(ISNUMBER(F43),ISNUMBER(I43),F43>0),I43/F43-1,"") | K43: 230 | L43: =IF(AND(ISNUMBER(F43),ISNUMBER(K43),F43>0),K43/F43-1,"") | M43: 15 | N43: 6.4 | O43: =IF(AND(ISNUMBER(F43),ISNUMBER(N43),F43>0),N43/F43,"") | P43: 46297 | Q43: 46316 | R43: 6.85 | S43: =IF(AND(ISNUMBER(F43),ISNUMBER(R43),R43>0),F43/R43,"") | T43: 46323
A44: AMAT | B44: Applied Materials, Inc. | C44: Semiconductor Equipment & Materials | D44: United States | E44: 314.21 | F44: 395.93 | G44: 627.8333 | H44: =IF(AND(ISNUMBER(F44),ISNUMBER(G44),F44>0),G44/F44-1,"") | I44: 358 | J44: =IF(AND(ISNUMBER(F44),ISNUMBER(I44),F44>0),I44/F44-1,"") | K44: 900 | L44: =IF(AND(ISNUMBER(F44),ISNUMBER(K44),F44>0),K44/F44-1,"") | M44: 36 | N44: 2.12 | O44: =IF(AND(ISNUMBER(F44),ISNUMBER(N44),F44>0),N44/F44,"") | P44: 46345 | Q44: 46338 | R44: 11.59 | S44: =IF(AND(ISNUMBER(F44),ISNUMBER(R44),R44>0),F44/R44,"") | T44: 46323
A45: GE | B45: GE Aerospace | C45: Aerospace & Defense | D45: United States | E45: 308.84 | F45: 297.66 | G45: 378.42856 | H45: =IF(AND(ISNUMBER(F45),ISNUMBER(G45),F45>0),G45/F45-1,"") | I45: 280 | J45: =IF(AND(ISNUMBER(F45),ISNUMBER(I45),F45>0),I45/F45-1,"") | K45: 431 | L45: =IF(AND(ISNUMBER(F45),ISNUMBER(K45),F45>0),K45/F45-1,"") | M45: 21 | N45: 1.88 | O45: =IF(AND(ISNUMBER(F45),ISNUMBER(N45),F45>0),N45/F45,"") | P45: 46300 | Q45: 46408 | R45: 8.75 | S45: =IF(AND(ISNUMBER(F45),ISNUMBER(R45),R45>0),F45/R45,"") | T45: 46323
A46: LRCX | B46: Lam Research Corporation | C46: Semiconductor Equipment & Materials | D46: United States | E46: 301.41 | F46: 240.85 | G46: 364.03333 | H46: =IF(AND(ISNUMBER(F46),ISNUMBER(G46),F46>0),G46/F46-1,"") | I46: 255 | J46: =IF(AND(ISNUMBER(F46),ISNUMBER(I46),F46>0),I46/F46-1,"") | K46: 500 | L46: =IF(AND(ISNUMBER(F46),ISNUMBER(K46),F46>0),K46/F46-1,"") | M46: 30 | N46: 1.32 | O46: =IF(AND(ISNUMBER(F46),ISNUMBER(N46),F46>0),N46/F46,"") | P46: 46288 | Q46: 46316 | R46: 6.93 | S46: =IF(AND(ISNUMBER(F46),ISNUMBER(R46),R46>0),F46/R46,"") | T46: 46323
A47: NVS | B47: Novartis AG | C47: Drug Manufacturers - General | D47: Switzerland | E47: 298.15 | F47: 156.86 | G47: 154.65 | H47: =IF(AND(ISNUMBER(F47),ISNUMBER(G47),F47>0),G47/F47-1,"") | I47: 130 | J47: =IF(AND(ISNUMBER(F47),ISNUMBER(I47),F47>0),I47/F47-1,"") | K47: 185 | L47: =IF(AND(ISNUMBER(F47),ISNUMBER(K47),F47>0),K47/F47-1,"") | M47: 11 | N47: 4.74 | O47: =IF(AND(ISNUMBER(F47),ISNUMBER(N47),F47>0),N47/F47,"") | P47: 46092 | Q47: 46322 | R47: 6.62 | S47: =IF(AND(ISNUMBER(F47),ISNUMBER(R47),R47>0),F47/R47,"") | T47: 46323
A48: SHEL | B48: Shell PLC | C48: Oil & Gas Integrated | D48: United Kingdom | E48: 297.56 | F48: 104.78 | G48: 105.56 | H48: =IF(AND(ISNUMBER(F48),ISNUMBER(G48),F48>0),G48/F48-1,"") | I48: 83 | J48: =IF(AND(ISNUMBER(F48),ISNUMBER(I48),F48>0),I48/F48-1,"") | K48: 123 | L48: =IF(AND(ISNUMBER(F48),ISNUMBER(K48),F48>0),K48/F48-1,"") | M48: 15 | N48: 3.12 | O48: =IF(AND(ISNUMBER(F48),ISNUMBER(N48),F48>0),N48/F48,"") | P48: 46248 | Q48: 46324 | R48: 8.95 | S48: =IF(AND(ISNUMBER(F48),ISNUMBER(R48),R48>0),F48/R48,"") | T48: 46323
A49: HSBC | B49: HSBC Holdings, plc. | C49: Banks - Diversified | D49: United Kingdom | E49: 294.15 | F49: 86.01 | G49: 105.01667 | H49: =IF(AND(ISNUMBER(F49),ISNUMBER(G49),F49>0),G49/F49-1,"") | I49: 101 | J49: =IF(AND(ISNUMBER(F49),ISNUMBER(I49),F49>0),I49/F49-1,"") | K49: 112.05 | L49: =IF(AND(ISNUMBER(F49),ISNUMBER(K49),F49>0),K49/F49-1,"") | M49: 3 | N49: 3.75 | O49: =IF(AND(ISNUMBER(F49),ISNUMBER(N49),F49>0),N49/F49,"") | P49: 46248 | Q49: 46322 | R49: 7 | S49: =IF(AND(ISNUMBER(F49),ISNUMBER(R49),R49>0),F49/R49,"") | T49: 46323
A50: MS | B50: Morgan Stanley | C50: Capital Markets | D50: United States | E50: 292.51 | F50: 186.91 | G50: 211.04546 | H50: =IF(AND(ISNUMBER(F50),ISNUMBER(G50),F50>0),G50/F50-1,"") | I50: 185 | J50: =IF(AND(ISNUMBER(F50),ISNUMBER(I50),F50>0),I50/F50-1,"") | K50: 262 | L50: =IF(AND(ISNUMBER(F50),ISNUMBER(K50),F50>0),K50/F50-1,"") | M50: 22 | N50: 4.6 | O50: =IF(AND(ISNUMBER(F50),ISNUMBER(N50),F50>0),N50/F50,"") | P50: 46325 | Q50: 46401 | R50: 12.61 | S50: =IF(AND(ISNUMBER(F50),ISNUMBER(R50),R50>0),F50/R50,"") | T50: 46323
A51: TXN | B51: Texas Instruments Incorporated | C51: Semiconductors | D51: United States | E51: 282.42 | F51: 308.91 | G51: 336.86206 | H51: =IF(AND(ISNUMBER(F51),ISNUMBER(G51),F51>0),G51/F51-1,"") | I51: 250 | J51: =IF(AND(ISNUMBER(F51),ISNUMBER(I51),F51>0),I51/F51-1,"") | K51: 400 | L51: =IF(AND(ISNUMBER(F51),ISNUMBER(K51),F51>0),K51/F51-1,"") | M51: 29 | N51: 6.08 | O51: =IF(AND(ISNUMBER(F51),ISNUMBER(N51),F51>0),N51/F51,"") | P51: 46325 | Q51: 46316 | R51: 7.71 | S51: =IF(AND(ISNUMBER(F51),ISNUMBER(R51),R51>0),F51/R51,"") | T51: 46323
A52: RY | B52: Royal Bank Of Canada | C52: Banks - Diversified | D52: Canada | E52: 281.07 | F52: 203.02 | G52: 212.10191 | H52: =IF(AND(ISNUMBER(F52),ISNUMBER(G52),F52>0),G52/F52-1,"") | I52: 185.12103 | J52: =IF(AND(ISNUMBER(F52),ISNUMBER(I52),F52>0),I52/F52-1,"") | K52: 233.28403 | L52: =IF(AND(ISNUMBER(F52),ISNUMBER(K52),F52>0),K52/F52-1,"") | M52: 3 | N52: 5.02 | O52: =IF(AND(ISNUMBER(F52),ISNUMBER(N52),F52>0),N52/F52,"") | P52: 46321 | Q52: 46359 | R52: 11.44 | S52: =IF(AND(ISNUMBER(F52),ISNUMBER(R52),R52>0),F52/R52,"") | T52: 46323
A53: CRWD | B53: CrowdStrike Holdings, Inc. | C53: Software - Infrastructure | D53: United States | E53: 274.44 | F53: 268.02 | G53: 247.25 | H53: =IF(AND(ISNUMBER(F53),ISNUMBER(G53),F53>0),G53/F53-1,"") | I53: 132 | J53: =IF(AND(ISNUMBER(F53),ISNUMBER(I53),F53>0),I53/F53-1,"") | K53: 325 | L53: =IF(AND(ISNUMBER(F53),ISNUMBER(K53),F53>0),K53/F53-1,"") | M53: 50 | O53: =IF(AND(ISNUMBER(F53),ISNUMBER(N53),F53>0),N53/F53,"") | Q53: 46357 | R53: 0.05 | S53: =IF(AND(ISNUMBER(F53),ISNUMBER(R53),R53>0),F53/R53,"") | T53: 46323
A54: SAP | B54: SAP SE | C54: Software - Application | D54: Germany | E54: 272.16 | F54: 235.8 | G54: 280.83334 | H54: =IF(AND(ISNUMBER(F54),ISNUMBER(G54),F54>0),G54/F54-1,"") | I54: 258 | J54: =IF(AND(ISNUMBER(F54),ISNUMBER(I54),F54>0),I54/F54-1,"") | K54: 333 | L54: =IF(AND(ISNUMBER(F54),ISNUMBER(K54),F54>0),K54/F54-1,"") | M54: 12 | N54: 2.93 | O54: =IF(AND(ISNUMBER(F54),ISNUMBER(N54),F54>0),N54/F54,"") | P54: 46147 | Q54: 46316 | R54: 8.03 | S54: =IF(AND(ISNUMBER(F54),ISNUMBER(R54),R54>0),F54/R54,"") | T54: 46323
A55: GS | B55: Goldman Sachs Group, Inc. (The) | C55: Capital Markets | D55: United States | E55: 265.48 | F55: 911.77 | G55: 1031.1428 | H55: =IF(AND(ISNUMBER(F55),ISNUMBER(G55),F55>0),G55/F55-1,"") | I55: 730 | J55: =IF(AND(ISNUMBER(F55),ISNUMBER(I55),F55>0),I55/F55-1,"") | K55: 1250 | L55: =IF(AND(ISNUMBER(F55),ISNUMBER(K55),F55>0),K55/F55-1,"") | M55: 21 | N55: 20 | O55: =IF(AND(ISNUMBER(F55),ISNUMBER(N55),F55>0),N55/F55,"") | P55: 46358 | Q55: 46406 | R55: 69.55 | S55: =IF(AND(ISNUMBER(F55),ISNUMBER(R55),R55>0),F55/R55,"") | T55: 46323
A56: AZN | B56: AstraZeneca PLC | C56: Drug Manufacturers - General | D56: United Kingdom | E56: 263.78 | F56: 170.08 | G56: 206.65833 | H56: =IF(AND(ISNUMBER(F56),ISNUMBER(G56),F56>0),G56/F56-1,"") | I56: 158 | J56: =IF(AND(ISNUMBER(F56),ISNUMBER(I56),F56>0),I56/F56-1,"") | K56: 240 | L56: =IF(AND(ISNUMBER(F56),ISNUMBER(K56),F56>0),K56/F56-1,"") | M56: 12 | N56: 3.2 | O56: =IF(AND(ISNUMBER(F56),ISNUMBER(N56),F56>0),N56/F56,"") | P56: 46241 | Q56: 46325 | R56: 6.69 | S56: =IF(AND(ISNUMBER(F56),ISNUMBER(R56),R56>0),F56/R56,"") | T56: 46323
A57: RTX | B57: RTX Corporation | C57: Aerospace & Defense | D57: United States | E57: 262.6 | F57: 194.6 | G57: 229.1739 | H57: =IF(AND(ISNUMBER(F57),ISNUMBER(G57),F57>0),G57/F57-1,"") | I57: 200 | J57: =IF(AND(ISNUMBER(F57),ISNUMBER(I57),F57>0),I57/F57-1,"") | K57: 250 | L57: =IF(AND(ISNUMBER(F57),ISNUMBER(K57),F57>0),K57/F57-1,"") | M57: 23 | N57: 2.92 | O57: =IF(AND(ISNUMBER(F57),ISNUMBER(N57),F57>0),N57/F57,"") | P57: 46248 | Q57: 46315 | R57: 6.15 | S57: =IF(AND(ISNUMBER(F57),ISNUMBER(R57),R57>0),F57/R57,"") | T57: 46323
A58: NFLX | B58: Netflix, Inc. | C58: Entertainment | D58: United States | E58: 260.33 | F58: 62.52 | G58: 84.76326 | H58: =IF(AND(ISNUMBER(F58),ISNUMBER(G58),F58>0),G58/F58-1,"") | I58: 57 | J58: =IF(AND(ISNUMBER(F58),ISNUMBER(I58),F58>0),I58/F58-1,"") | K58: 126 | L58: =IF(AND(ISNUMBER(F58),ISNUMBER(K58),F58>0),K58/F58-1,"") | M58: 43 | O58: =IF(AND(ISNUMBER(F58),ISNUMBER(N58),F58>0),N58/F58,"") | Q58: 46406 | R58: 3.46 | S58: =IF(AND(ISNUMBER(F58),ISNUMBER(R58),R58>0),F58/R58,"") | T58: 46323
A59: NSRGY | B59: Nestle S.A. | C59: Packaged Foods | D59: Switzerland | E59: 258.02 | F59: 100.31 | G59: 107.96 | H59: =IF(AND(ISNUMBER(F59),ISNUMBER(G59),F59>0),G59/F59-1,"") | I59: 92 | J59: =IF(AND(ISNUMBER(F59),ISNUMBER(I59),F59>0),I59/F59-1,"") | K59: 128 | L59: =IF(AND(ISNUMBER(F59),ISNUMBER(K59),F59>0),K59/F59-1,"") | M59: 5 | N59: 3.94 | O59: =IF(AND(ISNUMBER(F59),ISNUMBER(N59),F59>0),N59/F59,"") | P59: 46133 | Q59: 46072 | R59: 3.63 | S59: =IF(AND(ISNUMBER(F59),ISNUMBER(R59),R59>0),F59/R59,"") | T59: 46323
A60: TMO | B60: Thermo Fisher Scientific Inc | C60: Diagnostics & Research | D60: United States | E60: 256.24 | F60: 693.02 | G60: 750.92 | H60: =IF(AND(ISNUMBER(F60),ISNUMBER(G60),F60>0),G60/F60-1,"") | I60: 560 | J60: =IF(AND(ISNUMBER(F60),ISNUMBER(I60),F60>0),I60/F60-1,"") | K60: 830 | L60: =IF(AND(ISNUMBER(F60),ISNUMBER(K60),F60>0),K60/F60-1,"") | M60: 25 | N60: 1.88 | O60: =IF(AND(ISNUMBER(F60),ISNUMBER(N60),F60>0),N60/F60,"") | P60: 46280 | Q60: 46316 | R60: 18.96 | S60: =IF(AND(ISNUMBER(F60),ISNUMBER(R60),R60>0),F60/R60,"") | T60: 46323
A61: BABA | B61: Alibaba Group Holding Limited | C61: Internet Retail | D61: China | E61: 249.37 | F61: 100.24 | G61: 185.93835 | H61: =IF(AND(ISNUMBER(F61),ISNUMBER(G61),F61>0),G61/F61-1,"") | I61: 95.80372 | J61: =IF(AND(ISNUMBER(F61),ISNUMBER(I61),F61>0),I61/F61-1,"") | K61: 239.72446 | L61: =IF(AND(ISNUMBER(F61),ISNUMBER(K61),F61>0),K61/F61-1,"") | M61: 41 | N61: 1.05 | O61: =IF(AND(ISNUMBER(F61),ISNUMBER(N61),F61>0),N61/F61,"") | P61: 46184 | Q61: 46350 | R61: 4.13 | S61: =IF(AND(ISNUMBER(F61),ISNUMBER(R61),R61>0),F61/R61,"") | T61: 46323
A62: WFC | B62: Wells Fargo & Company | C62: Banks - Diversified | D62: United States | E62: 248.12 | F62: 82.66 | G62: 97.02083 | H62: =IF(AND(ISNUMBER(F62),ISNUMBER(G62),F62>0),G62/F62-1,"") | I62: 88 | J62: =IF(AND(ISNUMBER(F62),ISNUMBER(I62),F62>0),I62/F62-1,"") | K62: 108 | L62: =IF(AND(ISNUMBER(F62),ISNUMBER(K62),F62>0),K62/F62-1,"") | M62: 24 | N62: 2 | O62: =IF(AND(ISNUMBER(F62),ISNUMBER(N62),F62>0),N62/F62,"") | P62: 46241 | Q62: 46401 | R62: 7.09 | S62: =IF(AND(ISNUMBER(F62),ISNUMBER(R62),R62>0),F62/R62,"") | T62: 46323
A63: AMGN | B63: Amgen Inc. | C63: Drug Manufacturers - General | D63: United States | E63: 242.18 | F63: 447.95 | G63: 397.3231 | H63: =IF(AND(ISNUMBER(F63),ISNUMBER(G63),F63>0),G63/F63-1,"") | I63: 225 | J63: =IF(AND(ISNUMBER(F63),ISNUMBER(I63),F63>0),I63/F63-1,"") | K63: 500 | L63: =IF(AND(ISNUMBER(F63),ISNUMBER(K63),F63>0),K63/F63-1,"") | M63: 29 | N63: 10.08 | O63: =IF(AND(ISNUMBER(F63),ISNUMBER(N63),F63>0),N63/F63,"") | P63: 46255 | Q63: 46329 | R63: 16.1 | S63: =IF(AND(ISNUMBER(F63),ISNUMBER(R63),R63>0),F63/R63,"") | T63: 46323
A64: ARM | B64: Arm Holdings plc | C64: Semiconductors | D64: United Kingdom | E64: 242.01 | F64: 226.6 | G64: 290.705 | H64: =IF(AND(ISNUMBER(F64),ISNUMBER(G64),F64>0),G64/F64-1,"") | I64: 125 | J64: =IF(AND(ISNUMBER(F64),ISNUMBER(I64),F64>0),I64/F64-1,"") | K64: 500 | L64: =IF(AND(ISNUMBER(F64),ISNUMBER(K64),F64>0),K64/F64-1,"") | M64: 40 | O64: =IF(AND(ISNUMBER(F64),ISNUMBER(N64),F64>0),N64/F64,"") | Q64: 46330 | R64: 0.97 | S64: =IF(AND(ISNUMBER(F64),ISNUMBER(R64),R64>0),F64/R64,"") | T64: 46323
A65: GEV | B65: GE Vernova Inc. | C65: Specialty Industrial Machinery | D65: United States | E65: 238.39 | F65: 895.08 | G65: 1223.9697 | H65: =IF(AND(ISNUMBER(F65),ISNUMBER(G65),F65>0),G65/F65-1,"") | I65: 940 | J65: =IF(AND(ISNUMBER(F65),ISNUMBER(I65),F65>0),I65/F65-1,"") | K65: 1450 | L65: =IF(AND(ISNUMBER(F65),ISNUMBER(K65),F65>0),K65/F65-1,"") | M65: 33 | N65: 2 | O65: =IF(AND(ISNUMBER(F65),ISNUMBER(N65),F65>0),N65/F65,"") | P65: 46322 | Q65: 46323 | R65: 34.88 | S65: =IF(AND(ISNUMBER(F65),ISNUMBER(R65),R65>0),F65/R65,"") | T65: 46323
A66: IBM | B66: International Business Machines | C66: Information Technology Services | D66: United States | E66: 236.52 | F66: 250.25 | G66: 257.21652 | H66: =IF(AND(ISNUMBER(F66),ISNUMBER(G66),F66>0),G66/F66-1,"") | I66: 174 | J66: =IF(AND(ISNUMBER(F66),ISNUMBER(I66),F66>0),I66/F66-1,"") | K66: 300 | L66: =IF(AND(ISNUMBER(F66),ISNUMBER(K66),F66>0),K66/F66-1,"") | M66: 23 | N66: 6.76 | O66: =IF(AND(ISNUMBER(F66),ISNUMBER(N66),F66>0),N66/F66,"") | P66: 46336 | Q66: 46316 | R66: 11.72 | S66: =IF(AND(ISNUMBER(F66),ISNUMBER(R66),R66>0),F66/R66,"") | T66: 46323
A67: ANET | B67: Arista Networks, Inc. | C67: Computer Hardware | D67: United States | E67: 235.85 | F67: 187 | G67: 243.58655 | H67: =IF(AND(ISNUMBER(F67),ISNUMBER(G67),F67>0),G67/F67-1,"") | I67: 190 | J67: =IF(AND(ISNUMBER(F67),ISNUMBER(I67),F67>0),I67/F67-1,"") | K67: 290 | L67: =IF(AND(ISNUMBER(F67),ISNUMBER(K67),F67>0),K67/F67-1,"") | M67: 29 | O67: =IF(AND(ISNUMBER(F67),ISNUMBER(N67),F67>0),N67/F67,"") | Q67: 46329 | R67: 3.17 | S67: =IF(AND(ISNUMBER(F67),ISNUMBER(R67),R67>0),F67/R67,"") | T67: 46323
A68: LIN | B68: Linde plc | C68: Specialty Chemicals | D68: United Kingdom | E68: 234.48 | F68: 508.65 | G68: 545.2593 | H68: =IF(AND(ISNUMBER(F68),ISNUMBER(G68),F68>0),G68/F68-1,"") | I68: 400 | J68: =IF(AND(ISNUMBER(F68),ISNUMBER(I68),F68>0),I68/F68-1,"") | K68: 591 | L68: =IF(AND(ISNUMBER(F68),ISNUMBER(K68),F68>0),K68/F68-1,"") | M68: 27 | N68: 6.4 | O68: =IF(AND(ISNUMBER(F68),ISNUMBER(N68),F68>0),N68/F68,"") | P68: 46359 | Q68: 46324 | R68: 15.49 | S68: =IF(AND(ISNUMBER(F68),ISNUMBER(R68),R68>0),F68/R68,"") | T68: 46323
A69: TM | B69: Toyota Motor Corporation | C69: Auto Manufacturers | D69: Japan | E69: 231.51 | F69: 196.56 | G69: 234.07802 | H69: =IF(AND(ISNUMBER(F69),ISNUMBER(G69),F69>0),G69/F69-1,"") | I69: 230 | J69: =IF(AND(ISNUMBER(F69),ISNUMBER(I69),F69>0),I69/F69-1,"") | K69: 239.31209 | L69: =IF(AND(ISNUMBER(F69),ISNUMBER(K69),F69>0),K69/F69-1,"") | M69: 4 | N69: 6.27 | O69: =IF(AND(ISNUMBER(F69),ISNUMBER(N69),F69>0),N69/F69,"") | P69: 46112 | Q69: 46331 | R69: 22.76 | S69: =IF(AND(ISNUMBER(F69),ISNUMBER(R69),R69>0),F69/R69,"") | T69: 46323
A70: SIEGY | B70: Siemens AG | C70: Specialty Industrial Machinery | D70: Germany | E70: 226.59 | F70: 148.25 | G70: 175.6 | H70: =IF(AND(ISNUMBER(F70),ISNUMBER(G70),F70>0),G70/F70-1,"") | I70: 139 | J70: =IF(AND(ISNUMBER(F70),ISNUMBER(I70),F70>0),I70/F70-1,"") | K70: 195 | L70: =IF(AND(ISNUMBER(F70),ISNUMBER(K70),F70>0),K70/F70-1,"") | M70: 4 | N70: 3.17 | O70: =IF(AND(ISNUMBER(F70),ISNUMBER(N70),F70>0),N70/F70,"") | P70: 46066 | Q70: 46338 | R70: 5.83 | S70: =IF(AND(ISNUMBER(F70),ISNUMBER(R70),R70>0),F70/R70,"") | T70: 46323
A71: MRVL | B71: Marvell Technology, Inc. | C71: Semiconductors | D71: United States | E71: 218.9 | F71: 243.57 | G71: 341.43552 | H71: =IF(AND(ISNUMBER(F71),ISNUMBER(G71),F71>0),G71/F71-1,"") | I71: 229.95 | J71: =IF(AND(ISNUMBER(F71),ISNUMBER(I71),F71>0),I71/F71-1,"") | K71: 450 | L71: =IF(AND(ISNUMBER(F71),ISNUMBER(K71),F71>0),K71/F71-1,"") | M71: 43 | N71: 0.24 | O71: =IF(AND(ISNUMBER(F71),ISNUMBER(N71),F71>0),N71/F71,"") | P71: 46304 | Q71: 46357 | R71: 3.04 | S71: =IF(AND(ISNUMBER(F71),ISNUMBER(R71),R71>0),F71/R71,"") | T71: 46323
A72: SHOP | B72: Shopify Inc. | C72: Software - Application | D72: Canada | E72: 215.16 | F72: 165.81 | G72: 176.35417 | H72: =IF(AND(ISNUMBER(F72),ISNUMBER(G72),F72>0),G72/F72-1,"") | I72: 120 | J72: =IF(AND(ISNUMBER(F72),ISNUMBER(I72),F72>0),I72/F72-1,"") | K72: 220 | L72: =IF(AND(ISNUMBER(F72),ISNUMBER(K72),F72>0),K72/F72-1,"") | M72: 48 | O72: =IF(AND(ISNUMBER(F72),ISNUMBER(N72),F72>0),N72/F72,"") | Q72: 46329 | R72: 1.48 | S72: =IF(AND(ISNUMBER(F72),ISNUMBER(R72),R72>0),F72/R72,"") | T72: 46323
A73: LVMUY | B73: LVMH-Moet Hennessy Louis Vuitto | C73: Luxury Goods | D73: France | E73: 213.18 | F73: 86.49 | G73: 106.83333 | H73: =IF(AND(ISNUMBER(F73),ISNUMBER(G73),F73>0),G73/F73-1,"") | I73: 95.5 | J73: =IF(AND(ISNUMBER(F73),ISNUMBER(I73),F73>0),I73/F73-1,"") | K73: 121 | L73: =IF(AND(ISNUMBER(F73),ISNUMBER(K73),F73>0),K73/F73-1,"") | M73: 3 | N73: 3.04 | O73: =IF(AND(ISNUMBER(F73),ISNUMBER(N73),F73>0),N73/F73,"") | P73: 46356 | Q73: 46230 | R73: 5.12 | S73: =IF(AND(ISNUMBER(F73),ISNUMBER(R73),R73>0),F73/R73,"") | T73: 46323
A74: BHP | B74: BHP Group Limited | C74: Other Industrial Metals & Mining | D74: Australia | E74: 209.93 | F74: 82.6 | G74: 78.14286 | H74: =IF(AND(ISNUMBER(F74),ISNUMBER(G74),F74>0),G74/F74-1,"") | I74: 62 | J74: =IF(AND(ISNUMBER(F74),ISNUMBER(I74),F74>0),I74/F74-1,"") | K74: 96 | L74: =IF(AND(ISNUMBER(F74),ISNUMBER(K74),F74>0),K74/F74-1,"") | M74: 7 | N74: 3.96 | O74: =IF(AND(ISNUMBER(F74),ISNUMBER(N74),F74>0),N74/F74,"") | P74: 46269 | Q74: 46251 | R74: 3.86 | S74: =IF(AND(ISNUMBER(F74),ISNUMBER(R74),R74>0),F74/R74,"") | T74: 46323
A75: AXP | B75: American Express Company | C75: Credit Services | D75: United States | E75: 209.82 | F75: 312.91 | G75: 369.3156 | H75: =IF(AND(ISNUMBER(F75),ISNUMBER(G75),F75>0),G75/F75-1,"") | I75: 329 | J75: =IF(AND(ISNUMBER(F75),ISNUMBER(I75),F75>0),I75/F75-1,"") | K75: 450 | L75: =IF(AND(ISNUMBER(F75),ISNUMBER(K75),F75>0),K75/F75-1,"") | M75: 25 | N75: 3.8 | O75: =IF(AND(ISNUMBER(F75),ISNUMBER(N75),F75>0),N75/F75,"") | P75: 46304 | Q75: 46318 | R75: 16.48 | S75: =IF(AND(ISNUMBER(F75),ISNUMBER(R75),R75>0),F75/R75,"") | T75: 46323
A76: ADI | B76: Analog Devices, Inc. | C76: Semiconductors | D76: United States | E76: 206.11 | F76: 425.35 | G76: 472.4375 | H76: =IF(AND(ISNUMBER(F76),ISNUMBER(G76),F76>0),G76/F76-1,"") | I76: 365 | J76: =IF(AND(ISNUMBER(F76),ISNUMBER(I76),F76>0),I76/F76-1,"") | K76: 675 | L76: =IF(AND(ISNUMBER(F76),ISNUMBER(K76),F76>0),K76/F76-1,"") | M76: 32 | N76: 4.4 | O76: =IF(AND(ISNUMBER(F76),ISNUMBER(N76),F76>0),N76/F76,"") | P76: 46266 | Q76: 46350 | R76: 8.42 | S76: =IF(AND(ISNUMBER(F76),ISNUMBER(R76),R76>0),F76/R76,"") | T76: 46323
A77: TD | B77: Toronto Dominion Bank (The) | C77: Banks - Diversified | D77: Canada | E77: 205.4 | F77: 125.78 | G77: 121.1053 | H77: =IF(AND(ISNUMBER(F77),ISNUMBER(G77),F77>0),G77/F77-1,"") | I77: 96.64096 | J77: =IF(AND(ISNUMBER(F77),ISNUMBER(I77),F77>0),I77/F77-1,"") | K77: 137.07318 | L77: =IF(AND(ISNUMBER(F77),ISNUMBER(K77),F77>0),K77/F77-1,"") | M77: 3 | N77: 3.2 | O77: =IF(AND(ISNUMBER(F77),ISNUMBER(N77),F77>0),N77/F77,"") | P77: 46304 | Q77: 46359 | R77: 6.74 | S77: =IF(AND(ISNUMBER(F77),ISNUMBER(R77),R77>0),F77/R77,"") | T77: 46323
A78: TTE | B78: TotalEnergies SE | C78: Oil & Gas Integrated | D78: France | E78: 203.62 | F78: 92.35 | G78: 99.65 | H78: =IF(AND(ISNUMBER(F78),ISNUMBER(G78),F78>0),G78/F78-1,"") | I78: 81 | J78: =IF(AND(ISNUMBER(F78),ISNUMBER(I78),F78>0),I78/F78-1,"") | K78: 119 | L78: =IF(AND(ISNUMBER(F78),ISNUMBER(K78),F78>0),K78/F78-1,"") | M78: 10 | N78: 4.04 | O78: =IF(AND(ISNUMBER(F78),ISNUMBER(N78),F78>0),N78/F78,"") | P78: 46387 | Q78: 46324 | R78: 7.99 | S78: =IF(AND(ISNUMBER(F78),ISNUMBER(R78),R78>0),F78/R78,"") | T78: 46323
A79: C | B79: Citigroup, Inc. | C79: Banks - Diversified | D79: United States | E79: 203.08 | F79: 122.69 | G79: 150.7143 | H79: =IF(AND(ISNUMBER(F79),ISNUMBER(G79),F79>0),G79/F79-1,"") | I79: 127 | J79: =IF(AND(ISNUMBER(F79),ISNUMBER(I79),F79>0),I79/F79-1,"") | K79: 170 | L79: =IF(AND(ISNUMBER(F79),ISNUMBER(K79),F79>0),K79/F79-1,"") | M79: 21 | N79: 2.68 | O79: =IF(AND(ISNUMBER(F79),ISNUMBER(N79),F79>0),N79/F79,"") | P79: 46328 | Q79: 46401 | R79: 10.26 | S79: =IF(AND(ISNUMBER(F79),ISNUMBER(R79),R79>0),F79/R79,"") | T79: 46323
A80: KLAC | B80: KLA Corporation | C80: Semiconductor Equipment & Materials | D80: United States | E80: 200.53 | F80: 153.66 | G80: 232.38461 | H80: =IF(AND(ISNUMBER(F80),ISNUMBER(G80),F80>0),G80/F80-1,"") | I80: 175 | J80: =IF(AND(ISNUMBER(F80),ISNUMBER(I80),F80>0),I80/F80-1,"") | K80: 325 | L80: =IF(AND(ISNUMBER(F80),ISNUMBER(K80),F80>0),K80/F80-1,"") | M80: 26 | N80: 0.92 | O80: =IF(AND(ISNUMBER(F80),ISNUMBER(N80),F80>0),N80/F80,"") | P80: 46251 | Q80: 46323 | R80: 3.66 | S80: =IF(AND(ISNUMBER(F80),ISNUMBER(R80),R80>0),F80/R80,"") | T80: 46323
A81: CRM | B81: Salesforce, Inc. | C81: Software - Application | D81: United States | E81: 198.25 | F81: 240.89 | G81: 287.0836 | H81: =IF(AND(ISNUMBER(F81),ISNUMBER(G81),F81>0),G81/F81-1,"") | I81: 165 | J81: =IF(AND(ISNUMBER(F81),ISNUMBER(I81),F81>0),I81/F81-1,"") | K81: 475 | L81: =IF(AND(ISNUMBER(F81),ISNUMBER(K81),F81>0),K81/F81-1,"") | M81: 53 | N81: 1.76 | O81: =IF(AND(ISNUMBER(F81),ISNUMBER(N81),F81>0),N81/F81,"") | P81: 46282 | Q81: 46358 | R81: 10.93 | S81: =IF(AND(ISNUMBER(F81),ISNUMBER(R81),R81>0),F81/R81,"") | T81: 46323
A82: GILD | B82: Gilead Sciences, Inc. | C82: Drug Manufacturers - General | D82: United States | E82: 197.25 | F82: 159.08 | G82: 160.1923 | H82: =IF(AND(ISNUMBER(F82),ISNUMBER(G82),F82>0),G82/F82-1,"") | I82: 126 | J82: =IF(AND(ISNUMBER(F82),ISNUMBER(I82),F82>0),I82/F82-1,"") | K82: 185 | L82: =IF(AND(ISNUMBER(F82),ISNUMBER(K82),F82>0),K82/F82-1,"") | M82: 26 | N82: 3.28 | O82: =IF(AND(ISNUMBER(F82),ISNUMBER(N82),F82>0),N82/F82,"") | P82: 46280 | Q82: 46324 | R82: -2.65 | S82: =IF(AND(ISNUMBER(F82),ISNUMBER(R82),R82>0),F82/R82,"") | T82: 46323
A83: QCOM | B83: QUALCOMM Incorporated | C83: Semiconductors | D83: United States | E83: 196.66 | F83: 184.17 | G83: 196.3 | H83: =IF(AND(ISNUMBER(F83),ISNUMBER(G83),F83>0),G83/F83-1,"") | I83: 100 | J83: =IF(AND(ISNUMBER(F83),ISNUMBER(I83),F83>0),I83/F83-1,"") | K83: 400 | L83: =IF(AND(ISNUMBER(F83),ISNUMBER(K83),F83>0),K83/F83-1,"") | M83: 30 | N83: 3.68 | O83: =IF(AND(ISNUMBER(F83),ISNUMBER(N83),F83>0),N83/F83,"") | P83: 46359 | Q83: 46330 | R83: 8.64 | S83: =IF(AND(ISNUMBER(F83),ISNUMBER(R83),R83>0),F83/R83,"") | T83: 46323
A84: APH | B84: Amphenol Corporation | C84: Electronic Components | D84: United States | E84: 192.86 | F84: 78.21 | G84: 102.97368 | H84: =IF(AND(ISNUMBER(F84),ISNUMBER(G84),F84>0),G84/F84-1,"") | I84: 85 | J84: =IF(AND(ISNUMBER(F84),ISNUMBER(I84),F84>0),I84/F84-1,"") | K84: 116 | L84: =IF(AND(ISNUMBER(F84),ISNUMBER(K84),F84>0),K84/F84-1,"") | M84: 19 | N84: 0.5 | O84: =IF(AND(ISNUMBER(F84),ISNUMBER(N84),F84>0),N84/F84,"") | P84: 46287 | Q84: 46323 | R84: 2 | S84: =IF(AND(ISNUMBER(F84),ISNUMBER(R84),R84>0),F84/R84,"") | T84: 46323
A85: DIS | B85: Walt Disney Company (The) | C85: Entertainment | D85: United States | E85: 190.33 | F85: 110.23 | G85: 126.58281 | H85: =IF(AND(ISNUMBER(F85),ISNUMBER(G85),F85>0),G85/F85-1,"") | I85: 86 | J85: =IF(AND(ISNUMBER(F85),ISNUMBER(I85),F85>0),I85/F85-1,"") | K85: 144 | L85: =IF(AND(ISNUMBER(F85),ISNUMBER(K85),F85>0),K85/F85-1,"") | M85: 32 | N85: 1.5 | O85: =IF(AND(ISNUMBER(F85),ISNUMBER(N85),F85>0),N85/F85,"") | P85: 46203 | Q85: 46343 | R85: 4.85 | S85: =IF(AND(ISNUMBER(F85),ISNUMBER(R85),R85>0),F85/R85,"") | T85: 46323
A86: SNDK | B86: Sandisk Corporation | C86: Computer Hardware | D86: United States | E86: 188.59 | F86: 1304.84 | G86: 2143.8333 | H86: =IF(AND(ISNUMBER(F86),ISNUMBER(G86),F86>0),G86/F86-1,"") | I86: 1000 | J86: =IF(AND(ISNUMBER(F86),ISNUMBER(I86),F86>0),I86/F86-1,"") | K86: 3600 | L86: =IF(AND(ISNUMBER(F86),ISNUMBER(K86),F86>0),K86/F86-1,"") | M86: 24 | O86: =IF(AND(ISNUMBER(F86),ISNUMBER(N86),F86>0),N86/F86,"") | Q86: 46324 | R86: 73.76 | S86: =IF(AND(ISNUMBER(F86),ISNUMBER(R86),R86>0),F86/R86,"") | T86: 46323
A87: BLK | B87: BlackRock, Inc. | C87: Asset Management | D87: United States | E87: 184.58 | F87: 1136.05 | G87: 1351 | H87: =IF(AND(ISNUMBER(F87),ISNUMBER(G87),F87>0),G87/F87-1,"") | I87: 1250 | J87: =IF(AND(ISNUMBER(F87),ISNUMBER(I87),F87>0),I87/F87-1,"") | K87: 1531 | L87: =IF(AND(ISNUMBER(F87),ISNUMBER(K87),F87>0),K87/F87-1,"") | M87: 17 | N87: 22.92 | O87: =IF(AND(ISNUMBER(F87),ISNUMBER(N87),F87>0),N87/F87,"") | P87: 46273 | Q87: 46401 | R87: 43.92 | S87: =IF(AND(ISNUMBER(F87),ISNUMBER(R87),R87>0),F87/R87,"") | T87: 46323
A88: ALIZY | B88: Allianz SE | C88: Insurance - Diversified | D88: Germany | E88: 183.42 | F88: 48.36 | G88: 63.69212 | H88: =IF(AND(ISNUMBER(F88),ISNUMBER(G88),F88>0),G88/F88-1,"") | I88: 48.48425 | J88: =IF(AND(ISNUMBER(F88),ISNUMBER(I88),F88>0),I88/F88-1,"") | K88: 78.9 | L88: =IF(AND(ISNUMBER(F88),ISNUMBER(K88),F88>0),K88/F88-1,"") | M88: 2 | N88: 2 | O88: =IF(AND(ISNUMBER(F88),ISNUMBER(N88),F88>0),N88/F88,"") | P88: 46153 | Q88: 46338 | R88: 3.56 | S88: =IF(AND(ISNUMBER(F88),ISNUMBER(R88),R88>0),F88/R88,"") | T88: 46323
A89: VZ | B89: Verizon Communications Inc. | C89: Telecom Services | D89: United States | E89: 182.09 | F89: 43.93 | G89: 50.65 | H89: =IF(AND(ISNUMBER(F89),ISNUMBER(G89),F89>0),G89/F89-1,"") | I89: 44 | J89: =IF(AND(ISNUMBER(F89),ISNUMBER(I89),F89>0),I89/F89-1,"") | K89: 62 | L89: =IF(AND(ISNUMBER(F89),ISNUMBER(K89),F89>0),K89/F89-1,"") | M89: 22 | N89: 2.83 | O89: =IF(AND(ISNUMBER(F89),ISNUMBER(N89),F89>0),N89/F89,"") | P89: 46304 | Q89: 46321 | R89: 3.84 | S89: =IF(AND(ISNUMBER(F89),ISNUMBER(R89),R89>0),F89/R89,"") | T89: 46323
A90: PEP | B90: Pepsico, Inc. | C90: Beverages - Non-Alcoholic | D90: United States | E90: 181.93 | F90: 133.5 | G90: 141.59091 | H90: =IF(AND(ISNUMBER(F90),ISNUMBER(G90),F90>0),G90/F90-1,"") | I90: 106 | J90: =IF(AND(ISNUMBER(F90),ISNUMBER(I90),F90>0),I90/F90-1,"") | K90: 169 | L90: =IF(AND(ISNUMBER(F90),ISNUMBER(K90),F90>0),K90/F90-1,"") | M90: 22 | N90: 5.92 | O90: =IF(AND(ISNUMBER(F90),ISNUMBER(N90),F90>0),N90/F90,"") | P90: 46269 | Q90: 46303 | R90: 7.95 | S90: =IF(AND(ISNUMBER(F90),ISNUMBER(R90),R90>0),F90/R90,"") | T90: 46323
A91: SAN | B91: Banco Santander, S.A. Sponsored | C91: Banks - Diversified | D91: Spain | E91: 180.19 | F91: 12.47 | G91: 14.75667 | H91: =IF(AND(ISNUMBER(F91),ISNUMBER(G91),F91>0),G91/F91-1,"") | I91: 13 | J91: =IF(AND(ISNUMBER(F91),ISNUMBER(I91),F91>0),I91/F91-1,"") | K91: 15.7 | L91: =IF(AND(ISNUMBER(F91),ISNUMBER(K91),F91>0),K91/F91-1,"") | M91: 3 | N91: 0.28 | O91: =IF(AND(ISNUMBER(F91),ISNUMBER(N91),F91>0),N91/F91,"") | P91: 46325 | Q91: 46323 | R91: 1.03 | S91: =IF(AND(ISNUMBER(F91),ISNUMBER(R91),R91>0),F91/R91,"") | T91: 46323
A92: ABT | B92: Abbott Laboratories | C92: Medical Devices | D92: United States | E92: 178.4 | F92: 103.1 | G92: 118.52269 | H92: =IF(AND(ISNUMBER(F92),ISNUMBER(G92),F92>0),G92/F92-1,"") | I92: 100 | J92: =IF(AND(ISNUMBER(F92),ISNUMBER(I92),F92>0),I92/F92-1,"") | K92: 130 | L92: =IF(AND(ISNUMBER(F92),ISNUMBER(K92),F92>0),K92/F92-1,"") | M92: 26 | N92: 2.52 | O92: =IF(AND(ISNUMBER(F92),ISNUMBER(N92),F92>0),N92/F92,"") | P92: 46310 | Q92: 46316 | R92: 2.69 | S92: =IF(AND(ISNUMBER(F92),ISNUMBER(R92),R92>0),F92/R92,"") | T92: 46323
A93: UNP | B93: Union Pacific Corporation | C93: Railroads | D93: United States | E93: 178.15 | F93: 299.88 | G93: 331 | H93: =IF(AND(ISNUMBER(F93),ISNUMBER(G93),F93>0),G93/F93-1,"") | I93: 245 | J93: =IF(AND(ISNUMBER(F93),ISNUMBER(I93),F93>0),I93/F93-1,"") | K93: 375 | L93: =IF(AND(ISNUMBER(F93),ISNUMBER(K93),F93>0),K93/F93-1,"") | M93: 24 | N93: 5.68 | O93: =IF(AND(ISNUMBER(F93),ISNUMBER(N93),F93>0),N93/F93,"") | P93: 46265 | Q93: 46317 | R93: 12.82 | S93: =IF(AND(ISNUMBER(F93),ISNUMBER(R93),R93>0),F93/R93,"") | T93: 46323
A94: COP | B94: ConocoPhillips | C94: Oil & Gas E&P | D94: United States | E94: 177.75 | F94: 147.96 | G94: 151.48148 | H94: =IF(AND(ISNUMBER(F94),ISNUMBER(G94),F94>0),G94/F94-1,"") | I94: 126 | J94: =IF(AND(ISNUMBER(F94),ISNUMBER(I94),F94>0),I94/F94-1,"") | K94: 189 | L94: =IF(AND(ISNUMBER(F94),ISNUMBER(K94),F94>0),K94/F94-1,"") | M94: 27 | N94: 3.36 | O94: =IF(AND(ISNUMBER(F94),ISNUMBER(N94),F94>0),N94/F94,"") | P94: 46251 | Q94: 46331 | R94: 7.55 | S94: =IF(AND(ISNUMBER(F94),ISNUMBER(R94),R94>0),F94/R94,"") | T94: 46323
A95: MCD | B95: McDonald's Corporation | C95: Restaurants | D95: United States | E95: 176.54 | F95: 249.47 | G95: 291.68967 | H95: =IF(AND(ISNUMBER(F95),ISNUMBER(G95),F95>0),G95/F95-1,"") | I95: 230 | J95: =IF(AND(ISNUMBER(F95),ISNUMBER(I95),F95>0),I95/F95-1,"") | K95: 390 | L95: =IF(AND(ISNUMBER(F95),ISNUMBER(K95),F95>0),K95/F95-1,"") | M95: 29 | N95: 7.72 | O95: =IF(AND(ISNUMBER(F95),ISNUMBER(N95),F95>0),N95/F95,"") | P95: 46357 | Q95: 46330 | R95: 12.31 | S95: =IF(AND(ISNUMBER(F95),ISNUMBER(R95),R95>0),F95/R95,"") | T95: 46323
A96: NEE | B96: NextEra Energy, Inc. | C96: Utilities - Regulated Electric | D96: United States | E96: 172.86 | F96: 82.42 | G96: 94.57895 | H96: =IF(AND(ISNUMBER(F96),ISNUMBER(G96),F96>0),G96/F96-1,"") | I96: 56 | J96: =IF(AND(ISNUMBER(F96),ISNUMBER(I96),F96>0),I96/F96-1,"") | K96: 110 | L96: =IF(AND(ISNUMBER(F96),ISNUMBER(K96),F96>0),K96/F96-1,"") | M96: 19 | N96: 2.49 | O96: =IF(AND(ISNUMBER(F96),ISNUMBER(N96),F96>0),N96/F96,"") | P96: 46353 | Q96: 46316 | R96: 5.55 | S96: =IF(AND(ISNUMBER(F96),ISNUMBER(R96),R96>0),F96/R96,"") | T96: 46323
A97: DE | B97: Deere & Company | C97: Farm & Heavy Construction Machinery | D97: United States | E97: 172.45 | F97: 639.58 | G97: 694.0078 | H97: =IF(AND(ISNUMBER(F97),ISNUMBER(G97),F97>0),G97/F97-1,"") | I97: 500 | J97: =IF(AND(ISNUMBER(F97),ISNUMBER(I97),F97>0),I97/F97-1,"") | K97: 813.18 | L97: =IF(AND(ISNUMBER(F97),ISNUMBER(K97),F97>0),K97/F97-1,"") | M97: 23 | N97: 6.48 | O97: =IF(AND(ISNUMBER(F97),ISNUMBER(N97),F97>0),N97/F97,"") | P97: 46295 | Q97: 46351 | R97: 17.99 | S97: =IF(AND(ISNUMBER(F97),ISNUMBER(R97),R97>0),F97/R97,"") | T97: 46323
A98: NVO | B98: Novo Nordisk A/S | C98: Drug Manufacturers - General | D98: Denmark | E98: 170.61 | F98: 38.67 | G98: 44.822773 | H98: =IF(AND(ISNUMBER(F98),ISNUMBER(G98),F98>0),G98/F98-1,"") | I98: 39.507065 | J98: =IF(AND(ISNUMBER(F98),ISNUMBER(I98),F98>0),I98/F98-1,"") | K98: 61.415943 | L98: =IF(AND(ISNUMBER(F98),ISNUMBER(K98),F98>0),K98/F98-1,"") | M98: 12 | N98: 1.8 | O98: =IF(AND(ISNUMBER(F98),ISNUMBER(N98),F98>0),N98/F98,"") | P98: 46251 | Q98: 46330 | R98: 4.13 | S98: =IF(AND(ISNUMBER(F98),ISNUMBER(R98),R98>0),F98/R98,"") | T98: 46323
... A104: BUD | B104: Anheuser-Busch Inbev SA Sponsor | C104: Beverages - Brewers | D104: Belgium | E104: 160.23 | F104: 81.37 | G104: 95.25727 | H104: =IF(AND(ISNUMBER(F104),ISNUMBER(G104),F104>0),G104/F104-1,"") | I104: 85 | J104: =IF(AND(ISNUMBER(F104),ISNUMBER(I104),F104>0),I104/F104-1,"") | K104: 109 | L104: =IF(AND(ISNUMBER(F104),ISNUMBER(K104),F104>0),K104/F104-1,"") | M104: 11 | N104: 1.35 | O104: =IF(AND(ISNUMBER(F104),ISNUMBER(N104),F104>0),N104/F104,"") | P104: 46150 | Q104: 46324 | R104: 4.64 | S104: =IF(AND(ISNUMBER(F104),ISNUMBER(R104),R104>0),F104/R104,"") | T104: 46323
A105: NOW | B105: ServiceNow, Inc. | C105: Software - Application | D105: United States | E105: 160.02 | F105: 154.78 | G105: 156.53609 | H105: =IF(AND(ISNUMBER(F105),ISNUMBER(G105),F105>0),G105/F105-1,"") | I105: 72 | J105: =IF(AND(ISNUMBER(F105),ISNUMBER(I105),F105>0),I105/F105-1,"") | K105: 266 | L105: =IF(AND(ISNUMBER(F105),ISNUMBER(K105),F105>0),K105/F105-1,"") | M105: 46 | O105: =IF(AND(ISNUMBER(F105),ISNUMBER(N105),F105>0),N105/F105,"") | Q105: 46323 | R105: 1.6 | S105: =IF(AND(ISNUMBER(F105),ISNUMBER(R105),R105>0),F105/R105,"") | T105: 46323
...

Sheet Tickers
A1: Ticker | B1: Group | C1: HOW TO ADD A STOCK
A2: A | B2: S&P 100 / US | C2: This tab mirrors the ticker universe used by the automated refresh.
A3: AA | B3: S&P 100 / US | C3: To add or remove a stock: edit the tickers.txt file in the GitHub repo (one symbol per line),
A4: AAL | B4: S&P 100 / US | C4: or simply tell Claude (e.g. “add NFLX and COIN to my price targets sheet”).
A5: AAP | B5: S&P 100 / US | C5: The next scheduled refresh picks the change up automatically — no other edits needed.
A6: AAPL | B6: S&P 100 / US | C6: Note: use Yahoo-style symbols (BRK-B, not BRK.B) when editing tickers.txt.
A7: ABAT | B7: S&P 100 / US
A8: ABBV | B8: S&P 100 / US
A9: ABEV | B9: S&P 100 / US
A10: ABG | B10: S&P 100 / US
A11: ABNB | B11: S&P 100 / US
A12: ABT | B12: S&P 100 / US
A13: ACGL | B13: S&P 100 / US
A14: ACHC | B14: S&P 100 / US
A15: ACHR | B15: S&P 100 / US
A16: ACI | B16: S&P 100 / US
A17: ACIW | B17: S&P 100 / US
A18: ACN | B18: S&P 100 / US
... A1121: ZS | B1121: S&P 100 / US
